Metadata-Version: 1.1
Name: spirit.releaser
Version: 0.7.1
Summary: Plugins for release automation with zest.releaser.
Home-page: https://github.com/it-spirit/spirit.releaser
Author: it-spirit
Author-email: info@it-spir.it
License: BSD
Download-URL: http://pypi.python.org/pypi/spirit.releaser
Keywords: diazo,packaging,releasing
Platform: UNKNOWN
Classifier: Development Status :: 5 - Production/Stable
Classifier: Environment :: Console
Classifier: Intended Audience :: Developers
Classifier: License :: OSI Approved :: BSD License
Classifier: Natural Language :: English
Classifier: Operating System :: OS Independent
Classifier: Programming Language :: Python
Classifier: Programming Language :: Python :: 2.7
Classifier: Topic :: Software Development :: Code Generators
Classifier: Topic :: Utilities
